arfi_settings/__init__.py
arfi_settings/arfi_debug.py
arfi_settings/connectors.py
arfi_settings/constants.py
arfi_settings/descriptors.py
arfi_settings/entity.py
arfi_settings/errors.py
arfi_settings/handlers.py
arfi_settings/init_config.py
arfi_settings/main.py
arfi_settings/py.typed
arfi_settings/readers.py
arfi_settings/schemes.py
arfi_settings/storage.py
arfi_settings/types.py
arfi_settings/utils.py
arfi_settings/version.py
arfi_settings-0.4.0.dist-info/METADATA
arfi_settings-0.4.0.dist-info/WHEEL
arfi_settings-0.4.0.dist-info/licenses/LICENSE
arfi_settings-0.4.0.dist-info/RECORD
