Metadata-Version: 2.3
Name: arfi-settings
Version: 0.4.0
Summary: Flexible application settings management using pydantic.
Project-URL: Homepage, https://github.com/py-art/arfi-settings
Project-URL: Repository, https://github.com/py-art/arfi-settings
Author-email: Artur Filin <filartur@yandex.ru>
License: MIT
License-File: LICENSE
Classifier: Framework :: Pydantic
Classifier: Framework :: Pydantic :: 2
Classifier: Programming Language :: Python :: 3
Classifier: Programming Language :: Python :: 3.11
Classifier: Programming Language :: Python :: 3.12
Requires-Python: >=3.11
Requires-Dist: pydantic>=2.3.0
Requires-Dist: python-dotenv>=0.21.0
Provides-Extra: toml
Requires-Dist: tomli>=2.0.1; extra == 'toml'
Provides-Extra: yaml
Requires-Dist: pyyaml>=6.0.1; extra == 'yaml'
